cpputils-1.4.2.dist-info/RECORD
cpputils-1.4.2.dist-info/METADATA
cpputils-1.4.2.dist-info/WHEEL
cpputils-1.4.2.dist-info/top_level.txt
cpputils-1.4.2.dist-info/LICENSE.txt
cpputils/__init__.py
cpputils/_default_ca_path.py
cpputils/_types.py
cpputils/_cpputils.cpython-39-x86_64-linux-gnu.so
