Metadata-Version: 2.1
Name: cpputils
Version: 1.4.2
Summary: CPP-Utils Python Package for string and file operations
Home-page: https://github.com/semmjon/cpputils.git
Author: sgeist
Author-email: semjon.geist@ionos.com
Requires-Python: >=3.8
License-File: LICENSE.txt
Requires-Dist: Brotli (~=1.0.9)
Requires-Dist: cryptography (~=37.0.4)
Requires-Dist: keyring (~=23.7.0)
Provides-Extra: test
Requires-Dist: pytest (>=6.0) ; extra == 'test'
